{
  "main": {
    "id": "4ee65c2785860834",
    "type": "split",
    "children": [
      {
        "id": "83a7def32d96b1bd",
        "type": "tabs",
        "children": [
          {
            "id": "e5048d6f8c9c4031",
            "type": "leaf",
            "state": {
              "type": "markdown",
              "state": {
                "file": "2024/Frp内网穿透.md",
                "mode": "source",
                "source": false
              }
            }
          },
          {
            "id": "443734abd77f76fe",
            "type": "leaf",
            "state": {
              "type": "release-notes",
              "state": {
                "currentVersion": "1.6.3"
              }
            }
          }
        ],
        "currentTab": 1
      }
    ],
    "direction": "vertical"
  },
  "left": {
    "id": "73c46c69d8c322f0",
    "type": "split",
    "children": [
      {
        "id": "6f5b5a8c5a37ad21",
        "type": "tabs",
        "children": [
          {
            "id": "c219e2fb0e099c1b",
            "type": "leaf",
            "state": {
              "type": "file-explorer",
              "state": {
                "sortOrder": "alphabetical"
              }
            }
          },
          {
            "id": "622074c82812f148",
            "type": "leaf",
            "state": {
              "type": "search",
              "state": {
                "query": "frp",
                "matchingCase": true,
                "explainSearch": false,
                "collapseAll": false,
                "extraContext": false,
                "sortOrder": "alphabetical"
              }
            }
          },
          {
            "id": "1d9e32c56dda6a7f",
            "type": "leaf",
            "state": {
              "type": "bookmarks",
              "state": {}
            }
          }
        ]
      }
    ],
    "direction": "horizontal",
    "width": 300
  },
  "right": {
    "id": "43c35078f6eed464",
    "type": "split",
    "children": [
      {
        "id": "8d68f1cfd4b9966e",
        "type": "tabs",
        "children": [
          {
            "id": "561bd00119faf5b6",
            "type": "leaf",
            "state": {
              "type": "backlink",
              "state": {
                "file": "2024/Frp内网穿透.md",
                "collapseAll": false,
                "extraContext": false,
                "sortOrder": "alphabetical",
                "showSearch": false,
                "searchQuery": "",
                "backlinkCollapsed": false,
                "unlinkedCollapsed": true
              }
            }
          },
          {
            "id": "7732ab2a6c1885ff",
            "type": "leaf",
            "state": {
              "type": "outgoing-link",
              "state": {
                "file": "2024/Frp内网穿透.md",
                "linksCollapsed": false,
                "unlinkedCollapsed": true
              }
            }
          },
          {
            "id": "56d6f199570dc53d",
            "type": "leaf",
            "state": {
              "type": "tag",
              "state": {
                "sortOrder": "frequency",
                "useHierarchy": true
              }
            }
          },
          {
            "id": "ef54cad0155854e4",
            "type": "leaf",
            "state": {
              "type": "outline",
              "state": {
                "file": "2024/Frp内网穿透.md"
              }
            }
          },
          {
            "id": "d170f2d8b538a79e",
            "type": "leaf",
            "state": {
              "type": "advanced-tables-toolbar",
              "state": {}
            }
          }
        ],
        "currentTab": 3
      }
    ],
    "direction": "horizontal",
    "width": 300
  },
  "left-ribbon": {
    "hiddenItems": {
      "switcher:打开快速切换": false,
      "graph:查看关系图谱": false,
      "canvas:新建白板": false,
      "daily-notes:打开/创建今天的日记": false,
      "templates:插入模板": false,
      "obsidian-excalidraw-plugin:新建绘图文件": false,
      "table-editor-obsidian:Advanced Tables Toolbar": false,
      "command-palette:打开命令面板": false
    }
  },
  "active": "443734abd77f76fe",
  "lastOpenFiles": [
    "2024/Java 业务开发常见错误 100 例/结课测试 _ 关于Java业务开发的100个常见错误，你都明白其中缘由了吗？.md",
    "2024/Java 业务开发常见错误 100 例/结束语 _ 写代码时，如何才能尽量避免踩坑？.md",
    "2024/Java 业务开发常见错误 100 例/答疑篇：设计篇思考题答案合集.md",
    "2024/Java 业务开发常见错误 100 例/答疑篇：安全篇思考题答案合集.md",
    "2024/Java 业务开发常见错误 100 例/答疑篇：加餐篇思考题答案合集.md",
    "2024/Java 业务开发常见错误 100 例/答疑篇：代码篇思考题集锦（二）.md",
    "2024/Java 业务开发常见错误 100 例/答疑篇：代码篇思考题集锦（三）.md",
    "2024/Java 业务开发常见错误 100 例/答疑篇：代码篇思考题集锦（一）.md",
    "2024/Java 业务开发常见错误 100 例/开篇词、业务代码真的会有这么多坑？.md",
    "2024/Java 业务开发常见错误 100 例/38 _ 加餐8：Java程序从虚拟机迁移到Kubernetes的一些坑.md",
    "2024/Java 业务开发常见错误 100 例/37 _ 加餐7：程序员成长28计.md",
    "2024/Java 业务开发常见错误 100 例/36 _ 加餐6：这15年来，我是如何在工作中学习技术和英语的？.md",
    "2024/Java 业务开发常见错误 100 例/35 _ 加餐5：分析定位Java问题，一定要用好这些工具（二）.md",
    "2024/Java 业务开发常见错误 100 例/34 _ 加餐4：分析定位Java问题，一定要用好这些工具（一）.md",
    "2024/Java 业务开发常见错误 100 例/33 _ 加餐3：定位应用问题，排错套路很重要.md",
    "2024/Java 业务开发常见错误 100 例/32 _ 加餐2：带你吃透课程中Java 8的那些重要知识点（二）.md",
    "2024/Java 业务开发常见错误 100 例/31 _ 加餐1：带你吃透课程中Java 8的那些重要知识点（一）.md",
    "2024/Java 业务开发常见错误 100 例/30 _ 如何正确保存和传输敏感数据？.md",
    "2024/Java 业务开发常见错误 100 例/29 _ 数据和代码：数据就是数据，代码就是代码.md",
    "2024/Java 业务开发常见错误 100 例/28 _ 安全兜底：涉及钱时，必须考虑防刷、限量和防重.md",
    "2024/Java 业务开发常见错误 100 例/27 _ 数据源头：任何客户端的东西都不可信任.md",
    "2024/Java 业务开发常见错误 100 例/25、异步处理好用，但非常容易用错.md",
    "2024/Java 业务开发常见错误 100 例/24、业务代码写完，就意味着生产就绪了？.md",
    "2024/Java 业务开发常见错误 100 例/23、缓存设计：缓存可以锦上添花也可以落井下石.md",
    "2024/Java 业务开发常见错误 100 例/22、接口设计：系统间对话的语言，一定要统一.md",
    "2024/Java 业务开发常见错误 100 例/21、 代码重复：搞定代码重复的三个绝招.md",
    "2024/Java 业务开发常见错误 100 例",
    "obsidian/drafts/achieved/微信图片_20231225144506.png",
    "obsidian/drafts/achieved/JAVA的内存模型（JMM）.xmind",
    "obsidian/drafts/achieved",
    "obsidian/drafts/新建文件夹",
    "obsidian/drafts/assets/Pasted image 20240401130706.png",
    "2024/assets/Pasted image 20240401130706.png",
    "obsidian/drafts/assets",
    "Excalidraw/Drawing 2024-03-23 22.27.54.excalidraw.png",
    "未命名.canvas",
    "Excalidraw",
    "assets/Pasted image 20240323220934.png",
    "assets/Pasted image 20240323220632.png",
    "obsidian/drafts",
    "assets",
    "obsidian/daily/新建文本文档.txt",
    "obsidian/daily",
    "数据结构与算法/images/二分查找/image-20221125174155058-1697004146064-2.png"
  ]
}